pharmacelera_utils/__init__.py
pharmacelera_utils/commands.py
pharmacelera_utils/errors.py
pharmacelera_utils/launch.py
pharmacelera_utils/services.py
pharmacelera_utils/utils.py
pharmacelera_utils-0.2.2.dist-info/licenses/LICENSE
pharmacelera_utils-0.2.2.dist-info/METADATA
pharmacelera_utils-0.2.2.dist-info/WHEEL
pharmacelera_utils-0.2.2.dist-info/entry_points.txt
pharmacelera_utils-0.2.2.dist-info/top_level.txt
pharmacelera_utils-0.2.2.dist-info/RECORD
