Metadata-Version: 2.4
Name: pharmacelera_utils
Version: 0.2.2
Summary: Utility functions to execute pharmacelera scripts
Home-page: https://bitbucket.org/pharmacelera/api-examples.git
Author: Pharmacelera developers
Author-email: support@pharmacelera.com
License: Mozilla Public License Version 2.0
Classifier: Programming Language :: Python :: 3
Classifier: Operating System :: OS Independent
Requires-Python: >=3.9
License-File: LICENSE
Requires-Dist: requests==2.31.0
Requires-Dist: PyYAML==6.0.1
Requires-Dist: boto3==1.28.62
Requires-Dist: botocore==1.31.62
Dynamic: author
Dynamic: author-email
Dynamic: classifier
Dynamic: home-page
Dynamic: license
Dynamic: license-file
Dynamic: requires-dist
Dynamic: requires-python
Dynamic: summary
